{
  "updatedAt": "2026-07-11T21:58:24Z",
  "product": "sh-j001",
  "stats": {
    "total_reviews": 1184,
    "defect": 21,
    "improvement": 452,
    "praise": 679,
    "issue_defect": 5,
    "issue_return": 0
  },
  "top_clusters": [
    {
      "name": "ローラー・ヘッド",
      "impact": 125,
      "review_defect": 4,
      "review_improvement": 109,
      "issue_defect": 1,
      "issue_return": 0,
      "is_core_function": false
    },
    {
      "name": "吸引力",
      "impact": 118.5,
      "review_defect": 5,
      "review_improvement": 56,
      "issue_defect": 2,
      "issue_return": 0,
      "is_core_function": true
    },
    {
      "name": "充電・バッテリー",
      "impact": 82.5,
      "review_defect": 3,
      "review_improvement": 38,
      "issue_defect": 2,
      "issue_return": 0,
      "is_core_function": true
    },
    {
      "name": "ダストカップ",
      "impact": 68,
      "review_defect": 2,
      "review_improvement": 62,
      "issue_defect": 0,
      "issue_return": 0,
      "is_core_function": false
    },
    {
      "name": "重量・サイズ",
      "impact": 67,
      "review_defect": 0,
      "review_improvement": 67,
      "issue_defect": 0,
      "issue_return": 0,
      "is_core_function": false
    },
    {
      "name": "音・静音性",
      "impact": 39,
      "review_defect": 0,
      "review_improvement": 39,
      "issue_defect": 0,
      "issue_return": 0,
      "is_core_function": false
    }
  ],
  "summary_ja": {
    "headline": "吸引力・充電の核心機能に深刻不具合、早急対応が必要",
    "narrative": "1,184件のレビューのうち約38%が改善要望を含み、全体的な吸引力・使い勝手への評価は高い一方、吸引力の突然喪失や充電中のACアダプター高温化など核心機能に関わる深刻な不具合が複数報告されています。ローラー部品の脱落という安全上のリスクも確認されており、早急な対処が求められます。",
    "key_findings": [
      {
        "topic": "ローラー・ヘッド",
        "count": 114,
        "finding": "レビュー内訳（不具合4件・改善要望109件）。ブラシへの髪絡まりや狭所対応不足が多数指摘されるほか、使用開始1か月でローラー4個中2個が脱落し小児・ペットの誤飲リスクが生じた事例が報告されている。"
      },
      {
        "topic": "吸引力",
        "count": 63,
        "finding": "レビュー内訳（不具合5件・改善要望56件）。購入後8回程度の使用で壁際の米粒も吸えないほど吸引力が著しく低下した事例や、LED不点灯時に吸引力がまったく出ない事例が報告されており、基本機能の喪失に近い状態が確認されている。"
      },
      {
        "topic": "充電・バッテリー",
        "count": 43,
        "finding": "レビュー内訳（不具合3件・改善要望38件）。強モード使用時のバッテリー消耗の早さを訴える声が多く、充電中にACアダプターが高温になる安全上の懸念事例も報告されている。"
      }
    ],
    "actions": [
      "吸引力低下・LED誤作動の再現試験を実施し、モーターおよびスイッチ部品の仕様を工場と共同で見直す",
      "ACアダプターの発熱基準を再設定し、充電回路の安全検査工程を工場ラインに追加する",
      "ローラー固定構造を設計変更し、脱落防止の出荷前全数検査を工場と共同で導入する"
    ]
  },
  "summary_zh": {
    "headline": "吸力与充电核心功能出现严重故障，需立即处理",
    "narrative": "在1,184条评价中，约38%包含改善意见。整体上，用户对吸力和易用性评价较高，但同时有多起关于吸力突然丧失、充电时AC适配器过热等核心功能严重故障的报告。此外，还确认了滚轮零件脱落导致的安全风险，需要尽快采取应对措施。",
    "key_findings": [
      {
        "topic": "滚轮·吸头",
        "count": 114,
        "finding": "评价构成（故障4件·改善意见109件）。大量用户反映刷头缠绕头发及无法进入狭窄空间等问题，另有报告显示使用仅1个月后4个滚轮中有2个脱落，存在幼儿及宠物误吞的安全风险。"
      },
      {
        "topic": "吸力",
        "count": 63,
        "finding": "评价构成（故障5件·改善意见56件）。有报告显示购买后仅使用约8次吸力便严重下降，连墙角米粒都无法吸起，接近核心功能完全丧失；另有LED不亮时吸力完全消失的案例被确认。"
      },
      {
        "topic": "充电·电池",
        "count": 43,
        "finding": "评价构成（故障3件·改善意见38件）。强力模式下电池消耗过快的反馈较多，同时有充电时AC适配器过热的安全隐患案例被报告。"
      }
    ],
    "actions": [
      "对吸力下降及LED误动作进行复现测试，与工厂共同重新审视电机及开关部件规格",
      "重新设定AC适配器发热标准，与工厂共同在生产线上新增充电电路安全检查工序",
      "对滚轮固定结构进行设计变更，与工厂共同引入出货前全数防脱落检查"
    ]
  },
  "returns_summary": {
    "summary_ja": {
      "headline": "現時点で対応事項なし",
      "narrative": "現時点で報告された返品はありません。",
      "key_findings": [],
      "actions": []
    },
    "summary_zh": {
      "headline": "当前无需处理事项",
      "narrative": "目前没有收到任何退货报告。",
      "key_findings": [],
      "actions": []
    }
  },
  "defects_summary": {
    "summary_ja": {
      "headline": "安全性直結の不具合（部品脱落・発熱・怪我）を最優先で対処",
      "narrative": "全12件すべてが深刻度「高」の不具合報告であり、ローラー脱落による誤飲リスク・ACアダプター過熱・本体形状による出血など、人身安全に直結する案件が複数含まれる。また吸引力の急激な低下やカーペット上でのモーター停止が複数件報告されており、製品の基本機能が早期に失われるケースが目立つ。充電端子折損・バッテリー初期不良・スイッチ誤作動など電気・機構系の信頼性不足も広範囲に及んでいる。",
      "key_findings": [
        {
          "topic": "吸引力・カーペット対応",
          "count": 4,
          "finding": "8回使用で吸引力ほぼ喪失、ペット毛環境での即再発、カーペット上でのモーター停止が複数件報告"
        },
        {
          "topic": "安全性（脱落・怪我・発熱）",
          "count": 3,
          "finding": "ローラー脱落による誤飲リスク、ACアダプター過熱、ハンディ使用時の指出血と人身被害が集中"
        },
        {
          "topic": "充電・バッテリー",
          "count": 2,
          "finding": "充電端子が転倒1回で折損、バッテリー初期不良が出荷段階で発生し交換対応が必要"
        }
      ],
      "actions": [
        "ローラー固定構造とACアダプター耐熱設計を再設計し、安全基準適合を出荷前検査で確認する",
        "カーペット対応ロジックとフィルター目詰まり検知を改善し、吸引力の早期劣化を再現試験で検証する"
      ]
    },
    "summary_zh": {
      "headline": "优先处理涉及安全的缺陷（零件脱落、过热、人身伤害）",
      "narrative": "全部12件报告均为严重度「高」的缺陷，其中包含多起直接威胁人身安全的案例：滚轮脱落导致误食风险、AC适配器过热隐患、机身台阶造成手指出血。此外，多件报告反映吸力在短期使用后急剧下降，以及在地毯上使用时电机反复停转，产品基本功能丧失的情况较为突出。充电接口折断、电池初期不良、开关误动作等电气与机构可靠性问题也涉及范围较广。",
      "key_findings": [
        {
          "topic": "吸力与地毯适配",
          "count": 4,
          "finding": "使用约8次后吸力近乎丧失，宠物毛发环境下清空集尘杯后问题立即复现，地毯上电机反复停转"
        },
        {
          "topic": "安全性（脱落、受伤、过热）",
          "count": 3,
          "finding": "滚轮脱落存在误食风险，AC适配器过热，手持向上使用时机身台阶导致手指破损出血"
        },
        {
          "topic": "充电与电池",
          "count": 2,
          "finding": "直立充电时倾倒导致充电接口折断，电池初期不良在出货阶段即已发生并需更换处理"
        }
      ],
      "actions": [
        "重新设计滚轮固定结构与AC适配器耐热方案，并在出货检查中确认符合安全标准",
        "改进地毯适配逻辑与滤网堵塞检测机制，通过再现测试验证并解决吸力早期劣化问题"
      ]
    }
  },
  "issue_headlines": {
    "12": {
      "ja": "ローラー2個が使用中に脱落・誤飲リスクあり",
      "zh": "滚轮脱落存在误食风险"
    },
    "11": {
      "ja": "電源OFF時にスイッチが誤作動・吸引ムラあり",
      "zh": "关机状态下开关误触发且吸力不均"
    },
    "10": {
      "ja": "充電中にACアダプターが高温になる",
      "zh": "充电时AC适配器过热存安全隐患"
    },
    "9": {
      "ja": "8回使用で吸引力が著しく低下し機能喪失",
      "zh": "使用8次后吸力急剧下降近乎失效"
    },
    "8": {
      "ja": "初期セッティング時にバッテリー不良が発生",
      "zh": "初次安装发现电池部件初始不良"
    },
    "7": {
      "ja": "ペット毛環境でダストカップ未満時に吸引力低下",
      "zh": "宠物毛环境下集尘杯未满吸力即失效"
    },
    "6": {
      "ja": "絨毯・マット上で本体が作動しない",
      "zh": "在地毯和垫子上无法正常启动"
    },
    "5": {
      "ja": "ヘッドとパイプが嵌まらず使用中に抜ける恐れ",
      "zh": "吸头与管接口无法卡合易脱落"
    },
    "4": {
      "ja": "立て充電中の転倒で充電端子が1ヶ月で折損",
      "zh": "直立充电倾倒导致充电接口折断"
    },
    "3": {
      "ja": "絨毯使用時にモーターが繰り返し停止する",
      "zh": "在地毯上使用时电机反复停转"
    },
    "2": {
      "ja": "LED不点灯時に吸引力がまったく出ない",
      "zh": "LED不亮时完全无吸力疑似电路故障"
    },
    "1": {
      "ja": "ハンディ上向き使用時に指が傷つき出血する",
      "zh": "手持向上使用时机身棱角划伤手指出血"
    }
  }
}
